sec_yf/__init__.py
sec_yf/download_sec.py
sec_yf/sec_yf.py
sec_yf/yahoo_finance.py
sec_yf-0.1.3.dist-info/LICENSE
sec_yf-0.1.3.dist-info/METADATA
sec_yf-0.1.3.dist-info/WHEEL
sec_yf-0.1.3.dist-info/RECORD
