Metadata-Version: 2.1
Name: sec_yf
Version: 0.1.3
Summary: A package for downloading accounting and market data from SEC regulated companies.
License: MIT
Author: Juan F. Imbet
Requires-Python: >=3.9,<4.0
Classifier: License :: OSI Approved :: MIT License
Classifier: Programming Language :: Python :: 3
Classifier: Programming Language :: Python :: 3.9
Classifier: Programming Language :: Python :: 3.10
Classifier: Programming Language :: Python :: 3.11
Classifier: Programming Language :: Python :: 3.12
Requires-Dist: bs4 (>=0.0.2,<0.0.3)
Requires-Dist: pandas (<=2.2.2)
Requires-Dist: pyarrow (>=17.0.0,<18.0.0)
Requires-Dist: sec-cik-mapper (>=2.1.0,<3.0.0)
Requires-Dist: tqdm (>=4.66.6,<5.0.0)
Requires-Dist: yfinance (>=0.2.44,<0.3.0)
